{
  "_fv": 10,
  "_type": "dimension",
  "definition": {
    "portalFrame": {
      "value": "Blocks.REDSTONE_BLOCK"
    },
    "portalParticles": {
      "value": "PORTAL"
    },
    "portalLuminance": 0.0,
    "portalSound": {
      "value": "block.portal.ambient"
    },
    "igniterName": "Surge Lighter",
    "igniterTab": {
      "value": "CUSTOM:AtherTheDragonSurge"
    },
    "texture": "unnamed_1",
    "portalTexture": "unnamed",
    "enablePortal": true,
    "biomesInDimension": [
      {
        "value": "nether"
      },
      {
        "value": "plains"
      }
    ],
    "worldGenType": "Normal world gen",
    "mainFillerBlock": {
      "value": "CUSTOM:Block1"
    },
    "fluidBlock": {
      "value": "Blocks.FLOWING_LAVA"
    },
    "airColor": {
      "value": -65485,
      "falpha": 0.0
    },
    "canRespawnHere": true,
    "hasFog": true,
    "hasWeather": true,
    "isDark": false,
    "doesWaterVaporize": true,
    "sleepResult": "DENY",
    "hasSkyLight": true,
    "imitateOverworldBehaviour": true
  }
}